Metadata-Version: 2.4
Name: Firefly-III-API-Client
Version: 6.2.10.0
Summary: Firefly III API Client
Home-page: https://github.com/ms32035/firefly-iii-client
Author: Marcin Szymanski
Author-email: ms32035@gmail.com
License: AGPLv3
Keywords: OpenAPI,OpenAPI-Generator,Firefly III API Client
Requires-Dist: urllib3<3.0.0,>=1.25.3
Requires-Dist: python-dateutil>=2.8.2
Requires-Dist: pydantic>=2
Requires-Dist: typing-extensions>=4.7.1
Dynamic: author
Dynamic: author-email
Dynamic: description
Dynamic: description-content-type
Dynamic: home-page
Dynamic: keywords
Dynamic: license
Dynamic: requires-dist
Dynamic: summary
